MANIFEST.in
README.rst
setup.py
chungpy/__init__.py
chungpy/mdsp.py
chungpy/mmdsp.py
chungpy/tests.py
chungpy.egg-info/PKG-INFO
chungpy.egg-info/SOURCES.txt
chungpy.egg-info/dependency_links.txt
chungpy.egg-info/requires.txt
chungpy.egg-info/top_level.txt
docs/Makefile
docs/source/api.rst
docs/source/conf.py
docs/source/how-to.rst
docs/source/index.rst
docs/source/requirements.txt