Metadata-Version: 1.1
Name: chungpy
Version: 1.0.1
Summary: An implementation of Chung's linear-time algorithm for solution of the Maximum Density Segment Problem with extended applications
Home-page: https://bitbucket.org/CorinnaErnst/chungpy
Author: Corinna Ernst
Author-email: corinna.ernst@uni-due.de
License: MIT
Platform: UNKNOWN
Classifier: Development Status :: 4 - Beta
Classifier: Intended Audience :: Science/Research
Classifier: License :: OSI Approved :: MIT License
Classifier: Natural Language :: English
Classifier: Programming Language :: Python :: 3
Classifier: Topic :: Scientific/Engineering :: Bio-Informatics
